educore/__init__.py
educore-0.0.1.dist-info/METADATA
educore-0.0.1.dist-info/WHEEL
educore-0.0.1.dist-info/top_level.txt
educore-0.0.1.dist-info/RECORD
