Metadata-Version: 2.1
Name: educore
Version: 0.0.1
Summary: A package for educore
Home-page: https://github.com/
Author: ll
Author-email: 
Classifier: Programming Language :: Python :: 3
Classifier: License :: OSI Approved :: MIT License
Classifier: Operating System :: OS Independent
Requires-Python: >=3.4
